pymydumper/__about__.py
pymydumper/__init__.py
pymydumper/cli.py
pymydumper-0.0.1.dist-info/METADATA
pymydumper-0.0.1.dist-info/WHEEL
pymydumper-0.0.1.dist-info/entry_points.txt
pymydumper-0.0.1.dist-info/licenses/LICENSE
pymydumper-0.0.1.dist-info/RECORD
