Metadata-Version: 2.1
Name: pymydumper
Version: 0.0.1
Summary: A python-based tool to easily and quickly generate logical backups from MySQL-compatible databases
Project-URL: Documentation, https://github.com/delissonsilva/pymydumper#readme
Project-URL: Issues, https://github.com/delissonsilva/pymydumper/issues
Project-URL: Source, https://github.com/delissonsilva/pymydumper
Author-email: Delisson Silva <delisonjunio@gmail.com>
License-File: LICENSE
Classifier: Development Status :: 4 - Beta
Classifier: Programming Language :: Python
Classifier: Programming Language :: Python :: 3.7
Classifier: Programming Language :: Python :: 3.8
Classifier: Programming Language :: Python :: 3.9
Classifier: Programming Language :: Python :: 3.10
Classifier: Programming Language :: Python :: 3.11
Classifier: Programming Language :: Python :: Implementation :: CPython
Classifier: Programming Language :: Python :: Implementation :: PyPy
Requires-Python: >=3.7
